pyrcb/__init__.py
pyrcb/main.py
pyrcb/stress.py
pyrcb-0.1.2.dist-info/METADATA
pyrcb-0.1.2.dist-info/WHEEL
pyrcb-0.1.2.dist-info/top_level.txt
pyrcb-0.1.2.dist-info/RECORD
