Metadata-Version: 2.4
Name: pyrcb
Version: 0.1.2
Summary: A Python library for concrete beam analysis and design
Author-email: Alexius Academia <alexius.sayco.academia@gmail.com>
Project-URL: Homepage, https://github.com/alexiusacademia/concrete-beam
Project-URL: Documentation, https://github.com/alexiusacademia/concrete-beam#readme
Project-URL: Repository, https://github.com/alexiusacademia/concrete-beam
Project-URL: Issues, https://github.com/alexiusacademia/concrete-beam/issues
Keywords: concrete,beam,structural,engineering
Classifier: Development Status :: 3 - Alpha
Classifier: Intended Audience :: Developers
Classifier: Intended Audience :: Science/Research
Classifier: License :: OSI Approved :: MIT License
Classifier: Programming Language :: Python :: 3
Classifier: Programming Language :: Python :: 3.12
Classifier: Topic :: Scientific/Engineering
Requires-Python: >=3.12
Provides-Extra: dev
Requires-Dist: pytest>=7.0; extra == "dev"
Requires-Dist: pytest-cov>=4.0; extra == "dev"
Requires-Dist: black>=23.0; extra == "dev"
Requires-Dist: ruff>=0.1.0; extra == "dev"
